[{"Title":"Oemojisangjuui","Age Rating":"None"},{"Title":"Doggy God's Street","Age Rating":"None"},{"Title":"Dotto Koni-chan","Age Rating":"None"},{"Title":"Xue Ying Ling Zhu 2nd Season","Age Rating":"None"},{"Title":"RPG Densetsu Hepoi","Age Rating":"None"},{"Title":"Sayonara Watashi no Cramer Movie: First Touch","Age Rating":"None"},{"Title":"Oi! Ryouma","Age Rating":"None"},{"Title":"Kiddy Grade: Maelstrom","Age Rating":"None"},{"Title":"Dae Jang Geum: Jang Geum's Dream 2","Age Rating":"None"},{"Title":"Starmyu in Halloween","Age Rating":"None"},{"Title":"Kindaichi Shounen no Jikenbo Movie 2: Satsuriku no Deep Blue","Age Rating":"None"},{"Title":"Ma La Nu Pei","Age Rating":"None"},{"Title":"Bem Movie: Become Human","Age Rating":"None"},{"Title":"Karakuri Kiden: Hiwou Senki","Age Rating":"None"},{"Title":"Can Ci Pin: Fangzhu Xingkong","Age Rating":"None"},{"Title":"Ore wa Chokkaku","Age Rating":"None"},{"Title":"Fortune Dogs","Age Rating":"None"},{"Title":"Ginga Patrol PJ","Age Rating":"None"},{"Title":"Sakugasaku","Age Rating":"None"},{"Title":"Min Diao Ju Yi Wen Lu","Age Rating":"None"}]